whatsloon/__init__.py
whatsloon/address.py
whatsloon/audio.py
whatsloon/base.py
whatsloon/contact.py
whatsloon/contextual_reply.py
whatsloon/cta.py
whatsloon/document.py
whatsloon/flow.py
whatsloon/image.py
whatsloon/list.py
whatsloon/location.py
whatsloon/location_request.py
whatsloon/reaction.py
whatsloon/read_receipts.py
whatsloon/reply_buttons.py
whatsloon/sticker.py
whatsloon/template.py
whatsloon/text.py
whatsloon/typing_indicator.py
whatsloon/video.py
whatsloon-2.0.5.dist-info/licenses/LICENSE
whatsloon-2.0.5.dist-info/METADATA
whatsloon-2.0.5.dist-info/WHEEL
whatsloon-2.0.5.dist-info/top_level.txt
whatsloon-2.0.5.dist-info/RECORD
