Metadata-Version: 2.4
Name: whatsloon
Version: 2.0.5
Summary: A user-friendly Python wrapper for the WhatsApp Cloud API. Easily integrate WhatsApp messaging into your applications and enhance user engagement with streamlined workflows.
Home-page: https://github.com/maharanasarkar/whatsloon
Author: Maharana Sarkar
Author-email: Maharana Sarkar <maharana.sarkar2000@gmail.com>
License: MIT
Keywords: whatsloon,whatsloon-library,WhatsApp API in Python,whatsloon-python,WhatsApp Cloud API Wrapper
Classifier: Programming Language :: Python :: 3
Classifier: License :: OSI Approved :: MIT License
Classifier: Operating System :: OS Independent
Classifier: Intended Audience :: Developers
Requires-Python: >=3.9.6
License-File: LICENSE
Requires-Dist: requests
Requires-Dist: httpx
Dynamic: author
Dynamic: home-page
Dynamic: license-file
Dynamic: requires-python
